{"dataurl":"story_content/slides/60v2edlHkFF.swf","iosurl":"mobile/slides/60v2edlHkFF.gz","html5url":null,"title":"A little bit softer now","trackviews":true,"showmenuresulticon":false,"viewgroupid":"","historygroupid":"","videozoom":"","scrolling":false,"transition":"appear","transduration":0,"transdir":1,"wipetrans":false,"slidelock":false,"navindex":-1,"globalaudioid":"","thumbnailid":"","slidewindowbg":null,"presenterref":{"id":"none","videodata":null},"slidelayers":[{"__type":"slidelayer","hideobjectsondisplay":null,"depth":0,"modal":false,"pauseparent":false,"rotatexpos":547,"rotateypos":291,"tabindex":-1,"enableseek":true,"enablereplay":true,"lmsid":"","timeline":{"duration":189023,"events":[{"__type":"event","time":0,"actions":{"Actions":[{"__type":"show","transition":"appear","duration":0,"direction":0,"animationid":"","reverse":false,"objref":{"type":"string","value":"5qgoVfJtl5s"}},{"__type":"show","transition":"appear","duration":0,"direction":0,"animationid":"","reverse":false,"objref":{"type":"string","value":"68V8p7x6BIm"}},{"__type":"show","transition":"appear","duration":0,"direction":0,"animationid":"","reverse":false,"objref":{"type":"string","value":"6gN1uQf2NMJ"}},{"__type":"show","transition":"custom","duration":0,"direction":0,"animationid":"Entrance","reverse":false,"objref":{"type":"string","value":"5koiWFieEi6"}},{"__type":"show","transition":"custom","duration":0,"direction":0,"animationid":"Entrance","reverse":false,"objref":{"type":"string","value":"5pZyKHtVTOd"}}]}}]},"objects":{"Objects":[{"__type":"vectorshape","rotation":0,"acctype":"image","defaultaction":"","imagelib":[{"__type":"imagedata","assetId":0,"id":"01","url":"story_content/5YzHb8rOqw7_80_DX168_DY168.swf","type":"normal","alttext":"Station.png","lmstext":null,"width":139,"height":140,"altimage":null,"mobileimage":null,"mobiledx":0,"mobiledy":0,"mask":null,"maskref":null}],"shapemaskid":"","xpos":624,"ypos":254,"tabindex":4,"tabenabled":true,"xoffset":0,"yoffset":0,"rotatexpos":19,"rotateypos":19,"xscale":100,"yscale":100,"alpha":100,"depth":1,"scrolling":true,"shufflelock":false,"dragdrop":null,"dragpath":null,"dragrotation":null,"data":{"hotlinkid":"","accstate":0,"textdata":null,"imagedata":null,"swfdata":null,"videodata":null,"audiodata":null,"emfdata":null,"rectdata":null,"vectordata":{"left":0,"top":0,"right":38,"bottom":38,"alttext":"Station.png","lmstext":null,"pngfb":false,"pr":{"l":"Lib","i":13},"text":null},"html5data":{"url":null,"xpos":0,"ypos":0,"width":38,"height":38,"strokewidth":0,"mask":null}},"mask":null,"markerType":null,"width":38,"height":38,"resume":false,"usehandcursor":true,"background":null,"id":"5qgoVfJtl5s"},{"__type":"vectorshape","rotation":90,"acctype":"image","defaultaction":"","imagelib":[{"__type":"imagedata","assetId":1,"id":"01","url":"story_content/5zWEHREaska_80_DX508_DY508.swf","type":"normal","alttext":"croppedShip.png","lmstext":null,"width":211,"height":254,"altimage":null,"mobileimage":null,"mobiledx":0,"mobiledy":0,"mask":null,"maskref":null}],"shapemaskid":"","xpos":28,"ypos":247,"tabindex":3,"tabenabled":true,"xoffset":0,"yoffset":0,"rotatexpos":19,"rotateypos":22.5,"xscale":100,"yscale":100,"alpha":100,"depth":2,"scrolling":true,"shufflelock":false,"dragdrop":null,"dragpath":null,"dragrotation":null,"data":{"hotlinkid":"","accstate":0,"textdata":null,"imagedata":null,"swfdata":null,"videodata":null,"audiodata":null,"emfdata":null,"rectdata":null,"vectordata":{"left":0,"top":0,"right":38,"bottom":45,"alttext":"croppedShip.png","lmstext":null,"pngfb":false,"pr":{"l":"Lib","i":14},"text":null},"html5data":{"url":null,"xpos":0,"ypos":0,"width":38,"height":45,"strokewidth":0,"mask":null}},"mask":null,"animations":[{"__type":"animation","id":"5he2UyfyreL","duration":4000,"hidetextatstart":true,"animateshapewithtext":false,"tweens":[{"__type":"tween","time":0,"duration":4000,"alpha":null,"position":{"relativerotation":false,"relativestartpoint":false,"path":[{"__type":"segment","type":"line","anchora":{"x":"28","y":"247","dx":"0","dy":"0"},"controla":null,"controlb":null,"anchorb":{"x":"629.3328","y":"249","dx":"0","dy":"0"}}],"duration":4000,"easing":"cubic","easingdir":"easeinout"},"rotation":null,"scale":null,"mask":null,"color":null,"skew":null,"matrix":null}]}],"markerType":null,"width":38,"height":45,"resume":false,"usehandcursor":true,"background":null,"id":"68V8p7x6BIm","events":[{"__type":"oncollisionstart","targets":["_parent.5qgoVfJtl5s"],"actions":{"Actions":[{"__type":"show_slidelayer","hideothers":"oncomplete","transition":"appear","duration":0,"direction":1,"animationid":null,"reverse":false,"objref":{"type":"string","value":"_parent._parent.6WbUwY1N2W7"}}]}},{"__type":"oncollisionstart","targets":["_parent.5koiWFieEi6","_parent.5pZyKHtVTOd"],"actions":{"Actions":[{"__type":"show_slidelayer","hideothers":"oncomplete","transition":"appear","duration":0,"direction":1,"animationid":null,"reverse":false,"objref":{"type":"string","value":"_parent._parent.67w0T79iCZz"}}]}}]},{"__type":"vectorshape","rotation":0,"acctype":"button","defaultaction":"onrelease","textlib":[{"__type":"textdata","uniqueId":"5pkLv0loo00_-96447810","id":"01","linkid":"txt__default_6gN1uQf2NMJ","type":"vectortext","alttext":null,"lmstext":null,"xpos":0,"ypos":0,"width":0,"height":0,"shadowindex":-1,"vartext":null,"vectortext":{"left":0,"top":0,"right":62,"bottom":22,"alttext":null,"lmstext":null,"pngfb":false,"pr":{"l":"Lib","i":20},"text":null}},{"__type":"textdata","uniqueId":"5oSe400WJOw_-1425581574","id":"02","linkid":"txt__default_Disabled_6gN1uQf2NMJ","type":"vectortext","alttext":null,"lmstext":null,"xpos":0,"ypos":0,"width":0,"height":0,"shadowindex":-1,"vartext":null,"vectortext":{"left":0,"top":0,"right":62,"bottom":22,"alttext":null,"lmstext":null,"pngfb":false,"pr":{"l":"Lib","i":20},"text":null}},{"__type":"textdata","uniqueId":"6KsdeEhntWf_67054125","id":"03","linkid":"txt__default_Down_6gN1uQf2NMJ","type":"vectortext","alttext":null,"lmstext":null,"xpos":0,"ypos":0,"width":0,"height":0,"shadowindex":-1,"vartext":null,"vectortext":{"left":0,"top":0,"right":62,"bottom":22,"alttext":null,"lmstext":null,"pngfb":false,"pr":{"l":"Lib","i":20},"text":null}},{"__type":"textdata","uniqueId":"6YrwLpniYmb_1635556133","id":"04","linkid":"txt__default_Visited_6gN1uQf2NMJ","type":"vectortext","alttext":null,"lmstext":null,"xpos":0,"ypos":0,"width":0,"height":0,"shadowindex":-1,"vartext":null,"vectortext":{"left":0,"top":0,"right":62,"bottom":22,"alttext":null,"lmstext":null,"pngfb":false,"pr":{"l":"Lib","i":20},"text":null}},{"__type":"textdata","uniqueId":"5fihIcffR5p_-238059901","id":"05","linkid":"txt__default_Hover_6gN1uQf2NMJ","type":"vectortext","alttext":null,"lmstext":null,"xpos":0,"ypos":0,"width":0,"height":0,"shadowindex":-1,"vartext":null,"vectortext":{"left":0,"top":0,"right":62,"bottom":22,"alttext":null,"lmstext":null,"pngfb":false,"pr":{"l":"Lib","i":20},"text":null}}],"shapemaskid":"","xpos":33,"ypos":502,"tabindex":6,"tabenabled":true,"xoffset":0,"yoffset":0,"rotatexpos":36,"rotateypos":12,"xscale":100,"yscale":100,"alpha":100,"depth":3,"scrolling":true,"shufflelock":false,"dragdrop":null,"dragpath":null,"dragrotation":null,"data":{"hotlinkid":"","accstate":0,"textdata":null,"imagedata":null,"swfdata":null,"videodata":null,"audiodata":null,"emfdata":null,"rectdata":null,"vectordata":{"left":0,"top":0,"right":72,"bottom":24,"alttext":"Launch","lmstext":null,"pngfb":false,"pr":{"l":"Lib","i":15},"text":null},"html5data":{"url":null,"xpos":-1,"ypos":-1,"width":73,"height":25,"strokewidth":0,"mask":null}},"mask":null,"states":[{"__type":"state","name":"_default_Disabled","data":{"hotlinkid":"","accstate":1,"textdata":null,"imagedata":null,"swfdata":null,"videodata":null,"audiodata":null,"emfdata":null,"rectdata":null,"vectordata":{"left":0,"top":0,"right":72,"bottom":24,"alttext":"Launch","lmstext":null,"pngfb":false,"pr":{"l":"Lib","i":16},"text":null},"html5data":{"url":null,"xpos":0,"ypos":0,"width":72,"height":24,"strokewidth":0,"mask":null}}},{"__type":"state","name":"_default_Down","data":{"hotlinkid":"","accstate":8,"textdata":null,"imagedata":null,"swfdata":null,"videodata":null,"audiodata":null,"emfdata":null,"rectdata":null,"vectordata":{"left":0,"top":0,"right":72,"bottom":24,"alttext":"Launch","lmstext":null,"pngfb":false,"pr":{"l":"Lib","i":17},"text":null},"html5data":{"url":null,"xpos":0,"ypos":0,"width":72,"height":24,"strokewidth":0,"mask":null}}},{"__type":"state","name":"_default_Visited","data":{"hotlinkid":"","accstate":0,"textdata":null,"imagedata":null,"swfdata":null,"videodata":null,"audiodata":null,"emfdata":null,"rectdata":null,"vectordata":{"left":0,"top":0,"right":72,"bottom":24,"alttext":"Launch","lmstext":null,"pngfb":false,"pr":{"l":"Lib","i":18},"text":null},"html5data":{"url":null,"xpos":0,"ypos":0,"width":72,"height":24,"strokewidth":0,"mask":null}}},{"__type":"state","name":"_default_Visited_Disabled","data":{"hotlinkid":"","accstate":1,"textdata":null,"imagedata":null,"swfdata":null,"videodata":null,"audiodata":null,"emfdata":null,"rectdata":null,"vectordata":{"left":0,"top":0,"right":72,"bottom":24,"alttext":"Launch","lmstext":null,"pngfb":false,"pr":{"l":"Lib","i":16},"text":null},"html5data":{"url":null,"xpos":0,"ypos":0,"width":72,"height":24,"strokewidth":0,"mask":null}}},{"__type":"state","name":"_default_Down_Visited","data":{"hotlinkid":"","accstate":8,"textdata":null,"imagedata":null,"swfdata":null,"videodata":null,"audiodata":null,"emfdata":null,"rectdata":null,"vectordata":{"left":0,"top":0,"right":72,"bottom":24,"alttext":"Launch","lmstext":null,"pngfb":false,"pr":{"l":"Lib","i":17},"text":null},"html5data":{"url":null,"xpos":0,"ypos":0,"width":72,"height":24,"strokewidth":0,"mask":null}}},{"__type":"state","name":"_default_Hover","data":{"hotlinkid":"","accstate":0,"textdata":null,"imagedata":null,"swfdata":null,"videodata":null,"audiodata":null,"emfdata":null,"rectdata":null,"vectordata":{"left":0,"top":0,"right":72,"bottom":24,"alttext":"Launch","lmstext":null,"pngfb":false,"pr":{"l":"Lib","i":19},"text":null},"html5data":{"url":null,"xpos":0,"ypos":0,"width":72,"height":24,"strokewidth":0,"mask":null}}},{"__type":"state","name":"_default_Hover_Disabled","data":{"hotlinkid":"","accstate":1,"textdata":null,"imagedata":null,"swfdata":null,"videodata":null,"audiodata":null,"emfdata":null,"rectdata":null,"vectordata":{"left":0,"top":0,"right":72,"bottom":24,"alttext":"Launch","lmstext":null,"pngfb":false,"pr":{"l":"Lib","i":16},"text":null},"html5data":{"url":null,"xpos":0,"ypos":0,"width":72,"height":24,"strokewidth":0,"mask":null}}},{"__type":"state","name":"_default_Hover_Down","data":{"hotlinkid":"","accstate":8,"textdata":null,"imagedata":null,"swfdata":null,"videodata":null,"audiodata":null,"emfdata":null,"rectdata":null,"vectordata":{"left":0,"top":0,"right":72,"bottom":24,"alttext":"Launch","lmstext":null,"pngfb":false,"pr":{"l":"Lib","i":17},"text":null},"html5data":{"url":null,"xpos":0,"ypos":0,"width":72,"height":24,"strokewidth":0,"mask":null}}},{"__type":"state","name":"_default_Hover_Visited","data":{"hotlinkid":"","accstate":0,"textdata":null,"imagedata":null,"swfdata":null,"videodata":null,"audiodata":null,"emfdata":null,"rectdata":null,"vectordata":{"left":0,"top":0,"right":72,"bottom":24,"alttext":"Launch","lmstext":null,"pngfb":false,"pr":{"l":"Lib","i":19},"text":null},"html5data":{"url":null,"xpos":0,"ypos":0,"width":72,"height":24,"strokewidth":0,"mask":null}}},{"__type":"state","name":"_default_Hover_Visited_Disabled","data":{"hotlinkid":"","accstate":1,"textdata":null,"imagedata":null,"swfdata":null,"videodata":null,"audiodata":null,"emfdata":null,"rectdata":null,"vectordata":{"left":0,"top":0,"right":72,"bottom":24,"alttext":"Launch","lmstext":null,"pngfb":false,"pr":{"l":"Lib","i":16},"text":null},"html5data":{"url":null,"xpos":0,"ypos":0,"width":72,"height":24,"strokewidth":0,"mask":null}}},{"__type":"state","name":"_default_Hover_Down_Visited","data":{"hotlinkid":"","accstate":8,"textdata":null,"imagedata":null,"swfdata":null,"videodata":null,"audiodata":null,"emfdata":null,"rectdata":null,"vectordata":{"left":0,"top":0,"right":72,"bottom":24,"alttext":"Launch","lmstext":null,"pngfb":false,"pr":{"l":"Lib","i":17},"text":null},"html5data":{"url":null,"xpos":0,"ypos":0,"width":72,"height":24,"strokewidth":0,"mask":null}}}],"markerType":null,"width":72,"height":24,"resume":true,"usehandcursor":true,"background":null,"id":"6gN1uQf2NMJ","variables":[{"__type":"variable","name":"_hover","type":"boolean","value":false,"resume":true},{"__type":"variable","name":"_down","type":"boolean","value":false,"resume":true},{"__type":"variable","name":"_visited","type":"boolean","value":false,"resume":true},{"__type":"variable","name":"_disabled","type":"boolean","value":false,"resume":true},{"__type":"variable","name":"_savevisited","type":"boolean","value":false,"resume":true},{"__type":"variable","name":"_state","type":"string","value":"_default","resume":true},{"__type":"variable","name":"_stateName","type":"string","value":"","resume":true}],"actiongroups":[{"__type":"actiongroup","id":"ActGrpSetVisitedState","actions":{"Actions":[{"__type":"adjustvar","variable":"_savevisited","operator":"set","value":{"type":"var","value":"_visited"}},{"__type":"adjustvar","variable":"_visited","operator":"set","value":{"type":"boolean","value":true}},{"__type":"exe_actiongroup","id":"_player._setstates","scoperef":{"type":"string","value":"_this"},"params":null}]}},{"__type":"actiongroup","id":"ActGrpSetHoverState","actions":{"Actions":[{"__type":"adjustvar","variable":"_hover","operator":"set","value":{"type":"boolean","value":true}},{"__type":"exe_actiongroup","id":"_player._setstates","scoperef":{"type":"string","value":"_this"},"params":null}]}},{"__type":"actiongroup","id":"ActGrpClearHoverState","actions":{"Actions":[{"__type":"adjustvar","variable":"_hover","operator":"set","value":{"type":"boolean","value":false}},{"__type":"exe_actiongroup","id":"_player._setstates","scoperef":{"type":"string","value":"_this"},"params":null}]}},{"__type":"actiongroup","id":"ActGrpSetDisabledState","actions":{"Actions":[{"__type":"adjustvar","variable":"_disabled","operator":"set","value":{"type":"boolean","value":true}},{"__type":"exe_actiongroup","id":"_player._setstates","scoperef":{"type":"string","value":"_this"},"params":null}]}},{"__type":"actiongroup","id":"ActGrpSetDownState","actions":{"Actions":[{"__type":"adjustvar","variable":"_down","operator":"set","value":{"type":"boolean","value":true}},{"__type":"exe_actiongroup","id":"_player._setstates","scoperef":{"type":"string","value":"_this"},"params":null}]}},{"__type":"actiongroup","id":"ActGrpClearStateVars","actions":{"Actions":[{"__type":"adjustvar","variable":"_hover","operator":"set","value":{"type":"boolean","value":false}},{"__type":"adjustvar","variable":"_down","operator":"set","value":{"type":"boolean","value":false}},{"__type":"adjustvar","variable":"_visited","operator":"set","value":{"type":"boolean","value":false}},{"__type":"adjustvar","variable":"_disabled","operator":"set","value":{"type":"boolean","value":false}},{"__type":"adjustvar","variable":"_savevisited","operator":"set","value":{"type":"boolean","value":false}}]}}],"events":[{"__type":"onrelease","actions":{"Actions":[{"__type":"exe_actiongroup","id":"ActGrpSetVisitedState","scoperef":{"type":"string","value":"_this"},"params":null},{"__type":"adjustvar","variable":"_down","operator":"set","value":{"type":"boolean","value":false}},{"__type":"exe_actiongroup","id":"_player._setstates","scoperef":{"type":"string","value":"_this"},"params":null},{"__type":"if_action","condition":{"Statement":{"__type":"and","Statements":[{"__type":"and","Statements":[{"__type":"compare","operator":"eq","valuea":"_player.pressed","typea":"var","valueb":false,"typeb":"boolean"}]}]}},"then_actions":{"Actions":[{"__type":"exe_animation","id":"5he2UyfyreL","objref":{"type":"string","value":"_parent.68V8p7x6BIm"},"reverse":{"type":"boolean","value":false}}]},"else_actions":null},{"__type":"adjustvar","variable":"_player.pressed","operator":"set","value":{"type":"boolean","value":true}}]}},{"__type":"ontransitionin","actions":{"Actions":[{"__type":"exe_actiongroup","id":"_player._setstates","scoperef":{"type":"string","value":"_this"},"params":null}]}},{"__type":"onrollover","actions":{"Actions":[{"__type":"exe_actiongroup","id":"ActGrpSetHoverState","scoperef":{"type":"string","value":"_this"},"params":null}]}},{"__type":"onrollout","actions":{"Actions":[{"__type":"exe_actiongroup","id":"ActGrpClearHoverState","scoperef":{"type":"string","value":"_this"},"params":null}]}},{"__type":"onpress","actions":{"Actions":[{"__type":"exe_actiongroup","id":"ActGrpSetDownState","scoperef":{"type":"string","value":"_this"},"params":null}]}},{"__type":"onreleaseoutside","actions":{"Actions":[{"__type":"adjustvar","variable":"_down","operator":"set","value":{"type":"boolean","value":false}},{"__type":"exe_actiongroup","id":"_player._setstates","scoperef":{"type":"string","value":"_this"},"params":null}]}}]},{"__type":"vectorshape","rotation":0,"acctype":"image","defaultaction":"","imagelib":[{"__type":"imagedata","assetId":2,"id":"01","url":"story_content/6mkI2tqrq6Y_80_DX256_DY256.swf","type":"normal","alttext":"asteroid.png","lmstext":null,"width":128,"height":128,"altimage":null,"mobileimage":null,"mobiledx":0,"mobiledy":0,"mask":null,"maskref":null}],"shapemaskid":"","xpos":736,"ypos":200,"tabindex":2,"tabenabled":true,"xoffset":0,"yoffset":0,"rotatexpos":54,"rotateypos":54,"xscale":100,"yscale":100,"alpha":100,"depth":4,"scrolling":true,"shufflelock":false,"dragdrop":null,"dragpath":null,"dragrotation":null,"data":{"hotlinkid":"","accstate":0,"textdata":null,"imagedata":null,"swfdata":null,"videodata":null,"audiodata":null,"emfdata":null,"rectdata":null,"vectordata":{"left":0,"top":0,"right":108,"bottom":108,"alttext":"asteroid.png","lmstext":null,"pngfb":false,"pr":{"l":"Lib","i":43},"text":null},"html5data":{"url":null,"xpos":0,"ypos":0,"width":108,"height":108,"strokewidth":0,"mask":null}},"mask":null,"animations":[{"__type":"animation","id":"Entrance","duration":2000,"hidetextatstart":true,"animateshapewithtext":false,"tweens":[{"__type":"tween","time":0,"duration":2000,"alpha":null,"position":{"relativerotation":false,"relativestartpoint":false,"path":[{"__type":"segment","type":"cubic","anchora":{"x":"1025.682","y":"192.9987","dx":"0","dy":"0"},"controla":{"x":"1030.06","y":"266.561","dx":"0","dy":"0"},"controlb":{"x":"907.6921","y":"333.6902","dx":"0","dy":"0"},"anchorb":{"x":"752.3645","y":"342.9359","dx":"0","dy":"0"}},{"__type":"segment","type":"cubic","anchora":{"x":"752.3645","y":"342.9359","dx":"0","dy":"0"},"controla":{"x":"597.0368","y":"352.1817","dx":"0","dy":"0"},"controlb":{"x":"467.5692","y":"300.0428","dx":"0","dy":"0"},"anchorb":{"x":"463.1905","y":"226.4805","dx":"0","dy":"0"}},{"__type":"segment","type":"cubic","anchora":{"x":"463.1905","y":"226.4805","dx":"0","dy":"0"},"controla":{"x":"458.8118","y":"152.9181","dx":"0","dy":"0"},"controlb":{"x":"581.1801","y":"85.78898","dx":"0","dy":"0"},"anchorb":{"x":"736.5078","y":"76.5432","dx":"0","dy":"0"}},{"__type":"segment","type":"cubic","anchora":{"x":"736.5078","y":"76.5432","dx":"0","dy":"0"},"controla":{"x":"891.8353","y":"67.29748","dx":"0","dy":"0"},"controlb":{"x":"1021.303","y":"119.4364","dx":"0","dy":"0"},"anchorb":{"x":"1025.682","y":"192.9987","dx":"0","dy":"0"}}],"duration":2000,"easing":"linear","easingdir":"easein"},"rotation":null,"scale":null,"mask":null,"color":null,"skew":null,"matrix":null}]},{"__type":"animation","id":"Exit","duration":2000,"hidetextatstart":true,"animateshapewithtext":false,"tweens":[{"__type":"tween","time":0,"duration":2000,"alpha":null,"position":{"relativerotation":false,"relativestartpoint":false,"path":[{"__type":"segment","type":"cubic","anchora":{"x":"1025.682","y":"192.9987","dx":"0","dy":"0"},"controla":{"x":"1030.06","y":"266.561","dx":"0","dy":"0"},"controlb":{"x":"907.6921","y":"333.6902","dx":"0","dy":"0"},"anchorb":{"x":"752.3645","y":"342.9359","dx":"0","dy":"0"}},{"__type":"segment","type":"cubic","anchora":{"x":"752.3645","y":"342.9359","dx":"0","dy":"0"},"controla":{"x":"597.0368","y":"352.1817","dx":"0","dy":"0"},"controlb":{"x":"467.5692","y":"300.0428","dx":"0","dy":"0"},"anchorb":{"x":"463.1905","y":"226.4805","dx":"0","dy":"0"}},{"__type":"segment","type":"cubic","anchora":{"x":"463.1905","y":"226.4805","dx":"0","dy":"0"},"controla":{"x":"458.8118","y":"152.9181","dx":"0","dy":"0"},"controlb":{"x":"581.1801","y":"85.78898","dx":"0","dy":"0"},"anchorb":{"x":"736.5078","y":"76.5432","dx":"0","dy":"0"}},{"__type":"segment","type":"cubic","anchora":{"x":"736.5078","y":"76.5432","dx":"0","dy":"0"},"controla":{"x":"891.8353","y":"67.29748","dx":"0","dy":"0"},"controlb":{"x":"1021.303","y":"119.4364","dx":"0","dy":"0"},"anchorb":{"x":"1025.682","y":"192.9987","dx":"0","dy":"0"}}],"duration":2000,"easing":"linear","easingdir":"easein"},"rotation":null,"scale":null,"mask":null,"color":null,"skew":null,"matrix":null}]},{"__type":"animation","id":"5qFyfahSokg","duration":2000,"hidetextatstart":true,"animateshapewithtext":false,"tweens":[{"__type":"tween","time":0,"duration":2000,"alpha":null,"position":{"relativerotation":false,"relativestartpoint":false,"path":[{"__type":"segment","type":"cubic","anchora":{"x":"1025.682","y":"192.9987","dx":"0","dy":"0"},"controla":{"x":"1030.06","y":"266.561","dx":"0","dy":"0"},"controlb":{"x":"907.6921","y":"333.6902","dx":"0","dy":"0"},"anchorb":{"x":"752.3645","y":"342.9359","dx":"0","dy":"0"}},{"__type":"segment","type":"cubic","anchora":{"x":"752.3645","y":"342.9359","dx":"0","dy":"0"},"controla":{"x":"597.0368","y":"352.1817","dx":"0","dy":"0"},"controlb":{"x":"467.5692","y":"300.0428","dx":"0","dy":"0"},"anchorb":{"x":"463.1905","y":"226.4805","dx":"0","dy":"0"}},{"__type":"segment","type":"cubic","anchora":{"x":"463.1905","y":"226.4805","dx":"0","dy":"0"},"controla":{"x":"458.8118","y":"152.9181","dx":"0","dy":"0"},"controlb":{"x":"581.1801","y":"85.78898","dx":"0","dy":"0"},"anchorb":{"x":"736.5078","y":"76.5432","dx":"0","dy":"0"}},{"__type":"segment","type":"cubic","anchora":{"x":"736.5078","y":"76.5432","dx":"0","dy":"0"},"controla":{"x":"891.8353","y":"67.29748","dx":"0","dy":"0"},"controlb":{"x":"1021.303","y":"119.4364","dx":"0","dy":"0"},"anchorb":{"x":"1025.682","y":"192.9987","dx":"0","dy":"0"}}],"duration":2000,"easing":"linear","easingdir":"easein"},"rotation":null,"scale":null,"mask":null,"color":null,"skew":null,"matrix":null}]}],"markerType":null,"width":108,"height":108,"resume":false,"usehandcursor":true,"background":null,"id":"5koiWFieEi6","actiongroups":[{"__type":"actiongroup","id":"Entrance","actions":{"Actions":[{"__type":"exe_animation","id":"5qFyfahSokg","objref":{"type":"string","value":"_this"},"reverse":{"type":"boolean","value":false}}]}}],"events":[{"__type":"ontransitionin","actions":{"Actions":[]}},{"__type":"onanimationcomplete","id":"5qFyfahSokg","reverse":false,"actions":{"Actions":[{"__type":"exe_animation","id":"5qFyfahSokg","objref":{"type":"string","value":"_this"},"reverse":{"type":"boolean","value":false}}]}},{"__type":"onanimationcomplete","id":"Entrance","reverse":false,"actions":{"Actions":[{"__type":"exe_actiongroup","id":"Entrance","scoperef":null,"params":null}]}}]},{"__type":"vectorshape","rotation":0,"acctype":"image","defaultaction":"","imagelib":[{"__type":"imagedata","assetId":2,"id":"01","url":"story_content/6mkI2tqrq6Y_80_DX256_DY256.swf","type":"normal","alttext":"asteroid.png","lmstext":null,"width":128,"height":128,"altimage":null,"mobileimage":null,"mobiledx":0,"mobiledy":0,"mask":null,"maskref":null}],"shapemaskid":"","xpos":848,"ypos":430,"tabindex":5,"tabenabled":true,"xoffset":0,"yoffset":0,"rotatexpos":14,"rotateypos":14,"xscale":100,"yscale":100,"alpha":100,"depth":5,"scrolling":true,"shufflelock":false,"dragdrop":null,"dragpath":null,"dragrotation":null,"data":{"hotlinkid":"","accstate":0,"textdata":null,"imagedata":null,"swfdata":null,"videodata":null,"audiodata":null,"emfdata":null,"rectdata":null,"vectordata":{"left":0,"top":0,"right":28,"bottom":28,"alttext":"asteroid.png","lmstext":null,"pngfb":false,"pr":{"l":"Lib","i":46},"text":null},"html5data":{"url":null,"xpos":0,"ypos":0,"width":28,"height":28,"strokewidth":0,"mask":null}},"mask":null,"animations":[{"__type":"animation","id":"Entrance","duration":1660,"hidetextatstart":true,"animateshapewithtext":false,"tweens":[{"__type":"tween","time":0,"duration":1660,"alpha":null,"position":{"relativerotation":false,"relativestartpoint":false,"path":[{"__type":"segment","type":"cubic","anchora":{"x":"753.9999","y":"-85.92874","dx":"0","dy":"0"},"controla":{"x":"643.543","y":"-85.92874","dx":"0","dy":"0"},"controlb":{"x":"553.9999","y":"58.7276","dx":"0","dy":"0"},"anchorb":{"x":"553.9999","y":"237.17","dx":"0","dy":"0"}},{"__type":"segment","type":"cubic","anchora":{"x":"553.9999","y":"237.17","dx":"0","dy":"0"},"controla":{"x":"553.9999","y":"415.6125","dx":"0","dy":"0"},"controlb":{"x":"643.543","y":"560.2687","dx":"0","dy":"0"},"anchorb":{"x":"753.9999","y":"560.2687","dx":"0","dy":"0"}},{"__type":"segment","type":"cubic","anchora":{"x":"753.9999","y":"560.2687","dx":"0","dy":"0"},"controla":{"x":"864.4569","y":"560.2687","dx":"0","dy":"0"},"controlb":{"x":"953.9999","y":"415.6125","dx":"0","dy":"0"},"anchorb":{"x":"953.9999","y":"237.17","dx":"0","dy":"0"}},{"__type":"segment","type":"cubic","anchora":{"x":"953.9999","y":"237.17","dx":"0","dy":"0"},"controla":{"x":"953.9999","y":"58.72754","dx":"0","dy":"0"},"controlb":{"x":"864.4568","y":"-85.92874","dx":"0","dy":"0"},"anchorb":{"x":"753.9999","y":"-85.92874","dx":"0","dy":"0"}}],"duration":1660,"easing":"linear","easingdir":"easein"},"rotation":null,"scale":null,"mask":null,"color":null,"skew":null,"matrix":null}]},{"__type":"animation","id":"Exit","duration":1660,"hidetextatstart":true,"animateshapewithtext":false,"tweens":[{"__type":"tween","time":0,"duration":1660,"alpha":null,"position":{"relativerotation":false,"relativestartpoint":false,"path":[{"__type":"segment","type":"cubic","anchora":{"x":"753.9999","y":"-85.92874","dx":"0","dy":"0"},"controla":{"x":"643.543","y":"-85.92874","dx":"0","dy":"0"},"controlb":{"x":"553.9999","y":"58.7276","dx":"0","dy":"0"},"anchorb":{"x":"553.9999","y":"237.17","dx":"0","dy":"0"}},{"__type":"segment","type":"cubic","anchora":{"x":"553.9999","y":"237.17","dx":"0","dy":"0"},"controla":{"x":"553.9999","y":"415.6125","dx":"0","dy":"0"},"controlb":{"x":"643.543","y":"560.2687","dx":"0","dy":"0"},"anchorb":{"x":"753.9999","y":"560.2687","dx":"0","dy":"0"}},{"__type":"segment","type":"cubic","anchora":{"x":"753.9999","y":"560.2687","dx":"0","dy":"0"},"controla":{"x":"864.4569","y":"560.2687","dx":"0","dy":"0"},"controlb":{"x":"953.9999","y":"415.6125","dx":"0","dy":"0"},"anchorb":{"x":"953.9999","y":"237.17","dx":"0","dy":"0"}},{"__type":"segment","type":"cubic","anchora":{"x":"953.9999","y":"237.17","dx":"0","dy":"0"},"controla":{"x":"953.9999","y":"58.72754","dx":"0","dy":"0"},"controlb":{"x":"864.4568","y":"-85.92874","dx":"0","dy":"0"},"anchorb":{"x":"753.9999","y":"-85.92874","dx":"0","dy":"0"}}],"duration":1660,"easing":"linear","easingdir":"easein"},"rotation":null,"scale":null,"mask":null,"color":null,"skew":null,"matrix":null}]},{"__type":"animation","id":"61dOQFxy3Jw","duration":1660,"hidetextatstart":true,"animateshapewithtext":false,"tweens":[{"__type":"tween","time":0,"duration":1660,"alpha":null,"position":{"relativerotation":false,"relativestartpoint":false,"path":[{"__type":"segment","type":"cubic","anchora":{"x":"753.9999","y":"-85.92874","dx":"0","dy":"0"},"controla":{"x":"643.543","y":"-85.92874","dx":"0","dy":"0"},"controlb":{"x":"553.9999","y":"58.7276","dx":"0","dy":"0"},"anchorb":{"x":"553.9999","y":"237.17","dx":"0","dy":"0"}},{"__type":"segment","type":"cubic","anchora":{"x":"553.9999","y":"237.17","dx":"0","dy":"0"},"controla":{"x":"553.9999","y":"415.6125","dx":"0","dy":"0"},"controlb":{"x":"643.543","y":"560.2687","dx":"0","dy":"0"},"anchorb":{"x":"753.9999","y":"560.2687","dx":"0","dy":"0"}},{"__type":"segment","type":"cubic","anchora":{"x":"753.9999","y":"560.2687","dx":"0","dy":"0"},"controla":{"x":"864.4569","y":"560.2687","dx":"0","dy":"0"},"controlb":{"x":"953.9999","y":"415.6125","dx":"0","dy":"0"},"anchorb":{"x":"953.9999","y":"237.17","dx":"0","dy":"0"}},{"__type":"segment","type":"cubic","anchora":{"x":"953.9999","y":"237.17","dx":"0","dy":"0"},"controla":{"x":"953.9999","y":"58.72754","dx":"0","dy":"0"},"controlb":{"x":"864.4568","y":"-85.92874","dx":"0","dy":"0"},"anchorb":{"x":"753.9999","y":"-85.92874","dx":"0","dy":"0"}}],"duration":1660,"easing":"linear","easingdir":"easein"},"rotation":null,"scale":null,"mask":null,"color":null,"skew":null,"matrix":null}]}],"markerType":null,"width":28,"height":28,"resume":false,"usehandcursor":true,"background":null,"id":"5pZyKHtVTOd","actiongroups":[{"__type":"actiongroup","id":"Entrance","actions":{"Actions":[{"__type":"exe_animation","id":"61dOQFxy3Jw","objref":{"type":"string","value":"_this"},"reverse":{"type":"boolean","value":false}}]}}],"events":[{"__type":"onanimationcomplete","id":"61dOQFxy3Jw","reverse":false,"actions":{"Actions":[{"__type":"exe_animation","id":"61dOQFxy3Jw","objref":{"type":"string","value":"_this"},"reverse":{"type":"boolean","value":false}}]}},{"__type":"onanimationcomplete","id":"Entrance","reverse":false,"actions":{"Actions":[{"__type":"exe_actiongroup","id":"Entrance","scoperef":null,"params":null}]}},{"__type":"ontransitionin","actions":{"Actions":[]}}]}]},"starttime":-1,"elapsedtimemode":"normal","width":1095,"height":582,"resume":false,"usehandcursor":false,"background":null,"id":"5jE35qsKXif","events":[{"__type":"onslidestart","actions":{"Actions":[{"__type":"adjustvar","variable":"_player.pressed","operator":"set","value":{"type":"boolean","value":false}}]}}]},{"__type":"slidelayer","hideobjectsondisplay":null,"depth":0,"modal":false,"pauseparent":false,"rotatexpos":360,"rotateypos":270,"tabindex":-1,"enableseek":true,"enablereplay":true,"lmsid":"","timeline":{"duration":5000,"events":[{"__type":"event","time":0,"actions":{"Actions":[{"__type":"show","transition":"appear","duration":0,"direction":0,"animationid":"","reverse":false,"objref":{"type":"string","value":"6JeV1mmM38w"}}]}}]},"objects":{"Objects":[{"__type":"vectorshape","rotation":0,"acctype":"button","defaultaction":"onrelease","textlib":[{"__type":"textdata","uniqueId":"6OpFQjvxQbe_1359290502","id":"01","linkid":"txt__default_6JeV1mmM38w","type":"vectortext","alttext":null,"lmstext":null,"xpos":0,"ypos":0,"width":0,"height":0,"shadowindex":-1,"vartext":null,"vectortext":{"left":0,"top":0,"right":235,"bottom":110,"alttext":null,"lmstext":null,"pngfb":false,"pr":{"l":"Lib","i":26},"text":null}},{"__type":"textdata","uniqueId":"6JWyQJ2iw1q_-1651349091","id":"02","linkid":"txt__default_Disabled_6JeV1mmM38w","type":"vectortext","alttext":null,"lmstext":null,"xpos":0,"ypos":0,"width":0,"height":0,"shadowindex":-1,"vartext":null,"vectortext":{"left":0,"top":0,"right":235,"bottom":110,"alttext":null,"lmstext":null,"pngfb":false,"pr":{"l":"Lib","i":26},"text":null}},{"__type":"textdata","uniqueId":"6V0aKe8H4cI_505805403","id":"03","linkid":"txt__default_Down_6JeV1mmM38w","type":"vectortext","alttext":null,"lmstext":null,"xpos":0,"ypos":0,"width":0,"height":0,"shadowindex":-1,"vartext":null,"vectortext":{"left":0,"top":0,"right":235,"bottom":110,"alttext":null,"lmstext":null,"pngfb":false,"pr":{"l":"Lib","i":26},"text":null}},{"__type":"textdata","uniqueId":"6qsQwVMsrIz_-169155801","id":"04","linkid":"txt__default_Visited_6JeV1mmM38w","type":"vectortext","alttext":null,"lmstext":null,"xpos":0,"ypos":0,"width":0,"height":0,"shadowindex":-1,"vartext":null,"vectortext":{"left":0,"top":0,"right":235,"bottom":110,"alttext":null,"lmstext":null,"pngfb":false,"pr":{"l":"Lib","i":26},"text":null}},{"__type":"textdata","uniqueId":"5Yz3rEM5Xib_-1515120610","id":"05","linkid":"txt__default_Hover_6JeV1mmM38w","type":"vectortext","alttext":null,"lmstext":null,"xpos":0,"ypos":0,"width":0,"height":0,"shadowindex":-1,"vartext":null,"vectortext":{"left":0,"top":0,"right":235,"bottom":110,"alttext":null,"lmstext":null,"pngfb":false,"pr":{"l":"Lib","i":26},"text":null}}],"shapemaskid":"","xpos":160,"ypos":174,"tabindex":1,"tabenabled":true,"xoffset":0,"yoffset":0,"rotatexpos":196,"rotateypos":96,"xscale":100,"yscale":100,"alpha":100,"depth":1,"scrolling":true,"shufflelock":false,"dragdrop":null,"dragpath":null,"dragrotation":null,"data":{"hotlinkid":"","accstate":0,"textdata":null,"imagedata":null,"swfdata":null,"videodata":null,"audiodata":null,"emfdata":null,"rectdata":null,"vectordata":{"left":-1,"top":-1,"right":393,"bottom":193,"alttext":"Success!","lmstext":null,"pngfb":false,"pr":{"l":"Lib","i":21},"text":null},"html5data":{"url":null,"xpos":-1,"ypos":-1,"width":393,"height":193,"strokewidth":1,"mask":null}},"mask":null,"states":[{"__type":"state","name":"_default_Disabled","data":{"hotlinkid":"","accstate":1,"textdata":null,"imagedata":null,"swfdata":null,"videodata":null,"audiodata":null,"emfdata":null,"rectdata":null,"vectordata":{"left":-1,"top":-1,"right":393,"bottom":193,"alttext":"Success!","lmstext":null,"pngfb":false,"pr":{"l":"Lib","i":22},"text":null},"html5data":{"url":null,"xpos":-1,"ypos":-1,"width":394,"height":194,"strokewidth":1,"mask":null}}},{"__type":"state","name":"_default_Down","data":{"hotlinkid":"","accstate":8,"textdata":null,"imagedata":null,"swfdata":null,"videodata":null,"audiodata":null,"emfdata":null,"rectdata":null,"vectordata":{"left":-1,"top":-1,"right":393,"bottom":193,"alttext":"Success!","lmstext":null,"pngfb":false,"pr":{"l":"Lib","i":23},"text":null},"html5data":{"url":null,"xpos":-1,"ypos":-1,"width":394,"height":194,"strokewidth":1,"mask":null}}},{"__type":"state","name":"_default_Visited","data":{"hotlinkid":"","accstate":0,"textdata":null,"imagedata":null,"swfdata":null,"videodata":null,"audiodata":null,"emfdata":null,"rectdata":null,"vectordata":{"left":-1,"top":-1,"right":393,"bottom":193,"alttext":"Success!","lmstext":null,"pngfb":false,"pr":{"l":"Lib","i":24},"text":null},"html5data":{"url":null,"xpos":-1,"ypos":-1,"width":394,"height":194,"strokewidth":1,"mask":null}}},{"__type":"state","name":"_default_Visited_Disabled","data":{"hotlinkid":"","accstate":1,"textdata":null,"imagedata":null,"swfdata":null,"videodata":null,"audiodata":null,"emfdata":null,"rectdata":null,"vectordata":{"left":-1,"top":-1,"right":393,"bottom":193,"alttext":"Success!","lmstext":null,"pngfb":false,"pr":{"l":"Lib","i":22},"text":null},"html5data":{"url":null,"xpos":-1,"ypos":-1,"width":394,"height":194,"strokewidth":1,"mask":null}}},{"__type":"state","name":"_default_Down_Visited","data":{"hotlinkid":"","accstate":8,"textdata":null,"imagedata":null,"swfdata":null,"videodata":null,"audiodata":null,"emfdata":null,"rectdata":null,"vectordata":{"left":-1,"top":-1,"right":393,"bottom":193,"alttext":"Success!","lmstext":null,"pngfb":false,"pr":{"l":"Lib","i":23},"text":null},"html5data":{"url":null,"xpos":-1,"ypos":-1,"width":394,"height":194,"strokewidth":1,"mask":null}}},{"__type":"state","name":"_default_Hover","data":{"hotlinkid":"","accstate":0,"textdata":null,"imagedata":null,"swfdata":null,"videodata":null,"audiodata":null,"emfdata":null,"rectdata":null,"vectordata":{"left":-1,"top":-1,"right":393,"bottom":193,"alttext":"Success!","lmstext":null,"pngfb":false,"pr":{"l":"Lib","i":25},"text":null},"html5data":{"url":null,"xpos":-1,"ypos":-1,"width":394,"height":194,"strokewidth":1,"mask":null}}},{"__type":"state","name":"_default_Hover_Disabled","data":{"hotlinkid":"","accstate":1,"textdata":null,"imagedata":null,"swfdata":null,"videodata":null,"audiodata":null,"emfdata":null,"rectdata":null,"vectordata":{"left":-1,"top":-1,"right":393,"bottom":193,"alttext":"Success!","lmstext":null,"pngfb":false,"pr":{"l":"Lib","i":22},"text":null},"html5data":{"url":null,"xpos":-1,"ypos":-1,"width":394,"height":194,"strokewidth":1,"mask":null}}},{"__type":"state","name":"_default_Hover_Down","data":{"hotlinkid":"","accstate":8,"textdata":null,"imagedata":null,"swfdata":null,"videodata":null,"audiodata":null,"emfdata":null,"rectdata":null,"vectordata":{"left":-1,"top":-1,"right":393,"bottom":193,"alttext":"Success!","lmstext":null,"pngfb":false,"pr":{"l":"Lib","i":23},"text":null},"html5data":{"url":null,"xpos":-1,"ypos":-1,"width":394,"height":194,"strokewidth":1,"mask":null}}},{"__type":"state","name":"_default_Hover_Visited","data":{"hotlinkid":"","accstate":0,"textdata":null,"imagedata":null,"swfdata":null,"videodata":null,"audiodata":null,"emfdata":null,"rectdata":null,"vectordata":{"left":-1,"top":-1,"right":393,"bottom":193,"alttext":"Success!","lmstext":null,"pngfb":false,"pr":{"l":"Lib","i":25},"text":null},"html5data":{"url":null,"xpos":-1,"ypos":-1,"width":394,"height":194,"strokewidth":1,"mask":null}}},{"__type":"state","name":"_default_Hover_Visited_Disabled","data":{"hotlinkid":"","accstate":1,"textdata":null,"imagedata":null,"swfdata":null,"videodata":null,"audiodata":null,"emfdata":null,"rectdata":null,"vectordata":{"left":-1,"top":-1,"right":393,"bottom":193,"alttext":"Success!","lmstext":null,"pngfb":false,"pr":{"l":"Lib","i":22},"text":null},"html5data":{"url":null,"xpos":-1,"ypos":-1,"width":394,"height":194,"strokewidth":1,"mask":null}}},{"__type":"state","name":"_default_Hover_Down_Visited","data":{"hotlinkid":"","accstate":8,"textdata":null,"imagedata":null,"swfdata":null,"videodata":null,"audiodata":null,"emfdata":null,"rectdata":null,"vectordata":{"left":-1,"top":-1,"right":393,"bottom":193,"alttext":"Success!","lmstext":null,"pngfb":false,"pr":{"l":"Lib","i":23},"text":null},"html5data":{"url":null,"xpos":-1,"ypos":-1,"width":394,"height":194,"strokewidth":1,"mask":null}}}],"markerType":null,"width":392,"height":192,"resume":true,"usehandcursor":true,"background":null,"id":"6JeV1mmM38w","variables":[{"__type":"variable","name":"_hover","type":"boolean","value":false,"resume":true},{"__type":"variable","name":"_down","type":"boolean","value":false,"resume":true},{"__type":"variable","name":"_visited","type":"boolean","value":false,"resume":true},{"__type":"variable","name":"_disabled","type":"boolean","value":false,"resume":true},{"__type":"variable","name":"_savevisited","type":"boolean","value":false,"resume":true},{"__type":"variable","name":"_state","type":"string","value":"_default","resume":true},{"__type":"variable","name":"_stateName","type":"string","value":"","resume":true}],"actiongroups":[{"__type":"actiongroup","id":"ActGrpSetVisitedState","actions":{"Actions":[{"__type":"adjustvar","variable":"_savevisited","operator":"set","value":{"type":"var","value":"_visited"}},{"__type":"adjustvar","variable":"_visited","operator":"set","value":{"type":"boolean","value":true}},{"__type":"exe_actiongroup","id":"_player._setstates","scoperef":{"type":"string","value":"_this"},"params":null}]}},{"__type":"actiongroup","id":"ActGrpSetHoverState","actions":{"Actions":[{"__type":"adjustvar","variable":"_hover","operator":"set","value":{"type":"boolean","value":true}},{"__type":"exe_actiongroup","id":"_player._setstates","scoperef":{"type":"string","value":"_this"},"params":null}]}},{"__type":"actiongroup","id":"ActGrpClearHoverState","actions":{"Actions":[{"__type":"adjustvar","variable":"_hover","operator":"set","value":{"type":"boolean","value":false}},{"__type":"exe_actiongroup","id":"_player._setstates","scoperef":{"type":"string","value":"_this"},"params":null}]}},{"__type":"actiongroup","id":"ActGrpSetDisabledState","actions":{"Actions":[{"__type":"adjustvar","variable":"_disabled","operator":"set","value":{"type":"boolean","value":true}},{"__type":"exe_actiongroup","id":"_player._setstates","scoperef":{"type":"string","value":"_this"},"params":null}]}},{"__type":"actiongroup","id":"ActGrpSetDownState","actions":{"Actions":[{"__type":"adjustvar","variable":"_down","operator":"set","value":{"type":"boolean","value":true}},{"__type":"exe_actiongroup","id":"_player._setstates","scoperef":{"type":"string","value":"_this"},"params":null}]}},{"__type":"actiongroup","id":"ActGrpClearStateVars","actions":{"Actions":[{"__type":"adjustvar","variable":"_hover","operator":"set","value":{"type":"boolean","value":false}},{"__type":"adjustvar","variable":"_down","operator":"set","value":{"type":"boolean","value":false}},{"__type":"adjustvar","variable":"_visited","operator":"set","value":{"type":"boolean","value":false}},{"__type":"adjustvar","variable":"_disabled","operator":"set","value":{"type":"boolean","value":false}},{"__type":"adjustvar","variable":"_savevisited","operator":"set","value":{"type":"boolean","value":false}}]}}],"events":[{"__type":"onrelease","actions":{"Actions":[{"__type":"exe_actiongroup","id":"ActGrpSetVisitedState","scoperef":{"type":"string","value":"_this"},"params":null},{"__type":"adjustvar","variable":"_hover","operator":"set","value":{"type":"boolean","value":false}},{"__type":"adjustvar","variable":"_down","operator":"set","value":{"type":"boolean","value":false}},{"__type":"exe_actiongroup","id":"_player._setstates","scoperef":{"type":"string","value":"_this"},"params":null},{"__type":"gotoplay","window":"_current","wndtype":"normal","objref":{"type":"string","value":"_player.5hKLbrBpWRd.5ntSJEj2XS0"}}]}},{"__type":"ontransitionin","actions":{"Actions":[{"__type":"exe_actiongroup","id":"_player._setstates","scoperef":{"type":"string","value":"_this"},"params":null}]}},{"__type":"onrollover","actions":{"Actions":[{"__type":"exe_actiongroup","id":"ActGrpSetHoverState","scoperef":{"type":"string","value":"_this"},"params":null}]}},{"__type":"onrollout","actions":{"Actions":[{"__type":"exe_actiongroup","id":"ActGrpClearHoverState","scoperef":{"type":"string","value":"_this"},"params":null}]}},{"__type":"onpress","actions":{"Actions":[{"__type":"exe_actiongroup","id":"ActGrpSetDownState","scoperef":{"type":"string","value":"_this"},"params":null}]}},{"__type":"onreleaseoutside","actions":{"Actions":[{"__type":"adjustvar","variable":"_down","operator":"set","value":{"type":"boolean","value":false}},{"__type":"exe_actiongroup","id":"_player._setstates","scoperef":{"type":"string","value":"_this"},"params":null}]}}]}]},"starttime":-1,"elapsedtimemode":"normal","width":720,"height":540,"resume":true,"usehandcursor":false,"background":null,"id":"6WbUwY1N2W7"},{"__type":"slidelayer","hideobjectsondisplay":null,"depth":0,"modal":false,"pauseparent":false,"rotatexpos":360,"rotateypos":270,"tabindex":-1,"enableseek":true,"enablereplay":true,"lmsid":"","timeline":{"duration":5000,"events":[{"__type":"event","time":0,"actions":{"Actions":[{"__type":"show","transition":"appear","duration":0,"direction":0,"animationid":"","reverse":false,"objref":{"type":"string","value":"5bAmaDE3lC1"}}]}}]},"objects":{"Objects":[{"__type":"vectorshape","rotation":0,"acctype":"button","defaultaction":"onrelease","textlib":[{"__type":"textdata","uniqueId":"5qP3tfmTi3I_-715409254","id":"01","linkid":"txt__default_5bAmaDE3lC1","type":"vectortext","alttext":null,"lmstext":null,"xpos":0,"ypos":0,"width":0,"height":0,"shadowindex":-1,"vartext":null,"vectortext":{"left":0,"top":0,"right":234,"bottom":110,"alttext":null,"lmstext":null,"pngfb":false,"pr":{"l":"Lib","i":35},"text":null}},{"__type":"textdata","uniqueId":"6dpWw8jfyW7_-1075516489","id":"02","linkid":"txt__default_Disabled_5bAmaDE3lC1","type":"vectortext","alttext":null,"lmstext":null,"xpos":0,"ypos":0,"width":0,"height":0,"shadowindex":-1,"vartext":null,"vectortext":{"left":0,"top":0,"right":234,"bottom":110,"alttext":null,"lmstext":null,"pngfb":false,"pr":{"l":"Lib","i":35},"text":null}},{"__type":"textdata","uniqueId":"5qaeDKxyI9H_-1391464416","id":"03","linkid":"txt__default_Down_5bAmaDE3lC1","type":"vectortext","alttext":null,"lmstext":null,"xpos":0,"ypos":0,"width":0,"height":0,"shadowindex":-1,"vartext":null,"vectortext":{"left":0,"top":0,"right":234,"bottom":110,"alttext":null,"lmstext":null,"pngfb":false,"pr":{"l":"Lib","i":35},"text":null}},{"__type":"textdata","uniqueId":"6by3hqIhp0U_-1582868211","id":"04","linkid":"txt__default_Visited_5bAmaDE3lC1","type":"vectortext","alttext":null,"lmstext":null,"xpos":0,"ypos":0,"width":0,"height":0,"shadowindex":-1,"vartext":null,"vectortext":{"left":0,"top":0,"right":234,"bottom":110,"alttext":null,"lmstext":null,"pngfb":false,"pr":{"l":"Lib","i":35},"text":null}},{"__type":"textdata","uniqueId":"5vUyjwAfICg_793789796","id":"05","linkid":"txt__default_Hover_5bAmaDE3lC1","type":"vectortext","alttext":null,"lmstext":null,"xpos":0,"ypos":0,"width":0,"height":0,"shadowindex":-1,"vartext":null,"vectortext":{"left":0,"top":0,"right":234,"bottom":110,"alttext":null,"lmstext":null,"pngfb":false,"pr":{"l":"Lib","i":35},"text":null}}],"shapemaskid":"","xpos":168,"ypos":174,"tabindex":0,"tabenabled":true,"xoffset":0,"yoffset":0,"rotatexpos":192,"rotateypos":96,"xscale":100,"yscale":100,"alpha":100,"depth":1,"scrolling":true,"shufflelock":false,"dragdrop":null,"dragpath":null,"dragrotation":null,"data":{"hotlinkid":"","accstate":0,"textdata":null,"imagedata":null,"swfdata":null,"videodata":null,"audiodata":null,"emfdata":null,"rectdata":null,"vectordata":{"left":-1,"top":-1,"right":385,"bottom":193,"alttext":"Disaster!","lmstext":null,"pngfb":false,"pr":{"l":"Lib","i":30},"text":null},"html5data":{"url":null,"xpos":-1,"ypos":-1,"width":385,"height":193,"strokewidth":1,"mask":null}},"mask":null,"states":[{"__type":"state","name":"_default_Disabled","data":{"hotlinkid":"","accstate":1,"textdata":null,"imagedata":null,"swfdata":null,"videodata":null,"audiodata":null,"emfdata":null,"rectdata":null,"vectordata":{"left":-1,"top":-1,"right":385,"bottom":193,"alttext":"Disaster!","lmstext":null,"pngfb":false,"pr":{"l":"Lib","i":31},"text":null},"html5data":{"url":null,"xpos":-1,"ypos":-1,"width":386,"height":194,"strokewidth":1,"mask":null}}},{"__type":"state","name":"_default_Down","data":{"hotlinkid":"","accstate":8,"textdata":null,"imagedata":null,"swfdata":null,"videodata":null,"audiodata":null,"emfdata":null,"rectdata":null,"vectordata":{"left":-1,"top":-1,"right":385,"bottom":193,"alttext":"Disaster!","lmstext":null,"pngfb":false,"pr":{"l":"Lib","i":32},"text":null},"html5data":{"url":null,"xpos":-1,"ypos":-1,"width":386,"height":194,"strokewidth":1,"mask":null}}},{"__type":"state","name":"_default_Visited","data":{"hotlinkid":"","accstate":0,"textdata":null,"imagedata":null,"swfdata":null,"videodata":null,"audiodata":null,"emfdata":null,"rectdata":null,"vectordata":{"left":-1,"top":-1,"right":385,"bottom":193,"alttext":"Disaster!","lmstext":null,"pngfb":false,"pr":{"l":"Lib","i":33},"text":null},"html5data":{"url":null,"xpos":-1,"ypos":-1,"width":386,"height":194,"strokewidth":1,"mask":null}}},{"__type":"state","name":"_default_Visited_Disabled","data":{"hotlinkid":"","accstate":1,"textdata":null,"imagedata":null,"swfdata":null,"videodata":null,"audiodata":null,"emfdata":null,"rectdata":null,"vectordata":{"left":-1,"top":-1,"right":385,"bottom":193,"alttext":"Disaster!","lmstext":null,"pngfb":false,"pr":{"l":"Lib","i":31},"text":null},"html5data":{"url":null,"xpos":-1,"ypos":-1,"width":386,"height":194,"strokewidth":1,"mask":null}}},{"__type":"state","name":"_default_Down_Visited","data":{"hotlinkid":"","accstate":8,"textdata":null,"imagedata":null,"swfdata":null,"videodata":null,"audiodata":null,"emfdata":null,"rectdata":null,"vectordata":{"left":-1,"top":-1,"right":385,"bottom":193,"alttext":"Disaster!","lmstext":null,"pngfb":false,"pr":{"l":"Lib","i":32},"text":null},"html5data":{"url":null,"xpos":-1,"ypos":-1,"width":386,"height":194,"strokewidth":1,"mask":null}}},{"__type":"state","name":"_default_Hover","data":{"hotlinkid":"","accstate":0,"textdata":null,"imagedata":null,"swfdata":null,"videodata":null,"audiodata":null,"emfdata":null,"rectdata":null,"vectordata":{"left":-1,"top":-1,"right":385,"bottom":193,"alttext":"Disaster!","lmstext":null,"pngfb":false,"pr":{"l":"Lib","i":34},"text":null},"html5data":{"url":null,"xpos":-1,"ypos":-1,"width":386,"height":194,"strokewidth":1,"mask":null}}},{"__type":"state","name":"_default_Hover_Disabled","data":{"hotlinkid":"","accstate":1,"textdata":null,"imagedata":null,"swfdata":null,"videodata":null,"audiodata":null,"emfdata":null,"rectdata":null,"vectordata":{"left":-1,"top":-1,"right":385,"bottom":193,"alttext":"Disaster!","lmstext":null,"pngfb":false,"pr":{"l":"Lib","i":31},"text":null},"html5data":{"url":null,"xpos":-1,"ypos":-1,"width":386,"height":194,"strokewidth":1,"mask":null}}},{"__type":"state","name":"_default_Hover_Down","data":{"hotlinkid":"","accstate":8,"textdata":null,"imagedata":null,"swfdata":null,"videodata":null,"audiodata":null,"emfdata":null,"rectdata":null,"vectordata":{"left":-1,"top":-1,"right":385,"bottom":193,"alttext":"Disaster!","lmstext":null,"pngfb":false,"pr":{"l":"Lib","i":32},"text":null},"html5data":{"url":null,"xpos":-1,"ypos":-1,"width":386,"height":194,"strokewidth":1,"mask":null}}},{"__type":"state","name":"_default_Hover_Visited","data":{"hotlinkid":"","accstate":0,"textdata":null,"imagedata":null,"swfdata":null,"videodata":null,"audiodata":null,"emfdata":null,"rectdata":null,"vectordata":{"left":-1,"top":-1,"right":385,"bottom":193,"alttext":"Disaster!","lmstext":null,"pngfb":false,"pr":{"l":"Lib","i":34},"text":null},"html5data":{"url":null,"xpos":-1,"ypos":-1,"width":386,"height":194,"strokewidth":1,"mask":null}}},{"__type":"state","name":"_default_Hover_Visited_Disabled","data":{"hotlinkid":"","accstate":1,"textdata":null,"imagedata":null,"swfdata":null,"videodata":null,"audiodata":null,"emfdata":null,"rectdata":null,"vectordata":{"left":-1,"top":-1,"right":385,"bottom":193,"alttext":"Disaster!","lmstext":null,"pngfb":false,"pr":{"l":"Lib","i":31},"text":null},"html5data":{"url":null,"xpos":-1,"ypos":-1,"width":386,"height":194,"strokewidth":1,"mask":null}}},{"__type":"state","name":"_default_Hover_Down_Visited","data":{"hotlinkid":"","accstate":8,"textdata":null,"imagedata":null,"swfdata":null,"videodata":null,"audiodata":null,"emfdata":null,"rectdata":null,"vectordata":{"left":-1,"top":-1,"right":385,"bottom":193,"alttext":"Disaster!","lmstext":null,"pngfb":false,"pr":{"l":"Lib","i":32},"text":null},"html5data":{"url":null,"xpos":-1,"ypos":-1,"width":386,"height":194,"strokewidth":1,"mask":null}}}],"markerType":null,"width":384,"height":192,"resume":true,"usehandcursor":true,"background":null,"id":"5bAmaDE3lC1","variables":[{"__type":"variable","name":"_hover","type":"boolean","value":false,"resume":true},{"__type":"variable","name":"_down","type":"boolean","value":false,"resume":true},{"__type":"variable","name":"_visited","type":"boolean","value":false,"resume":true},{"__type":"variable","name":"_disabled","type":"boolean","value":false,"resume":true},{"__type":"variable","name":"_savevisited","type":"boolean","value":false,"resume":true},{"__type":"variable","name":"_state","type":"string","value":"_default","resume":true},{"__type":"variable","name":"_stateName","type":"string","value":"","resume":true}],"actiongroups":[{"__type":"actiongroup","id":"ActGrpSetVisitedState","actions":{"Actions":[{"__type":"adjustvar","variable":"_savevisited","operator":"set","value":{"type":"var","value":"_visited"}},{"__type":"adjustvar","variable":"_visited","operator":"set","value":{"type":"boolean","value":true}},{"__type":"exe_actiongroup","id":"_player._setstates","scoperef":{"type":"string","value":"_this"},"params":null}]}},{"__type":"actiongroup","id":"ActGrpSetHoverState","actions":{"Actions":[{"__type":"adjustvar","variable":"_hover","operator":"set","value":{"type":"boolean","value":true}},{"__type":"exe_actiongroup","id":"_player._setstates","scoperef":{"type":"string","value":"_this"},"params":null}]}},{"__type":"actiongroup","id":"ActGrpClearHoverState","actions":{"Actions":[{"__type":"adjustvar","variable":"_hover","operator":"set","value":{"type":"boolean","value":false}},{"__type":"exe_actiongroup","id":"_player._setstates","scoperef":{"type":"string","value":"_this"},"params":null}]}},{"__type":"actiongroup","id":"ActGrpSetDisabledState","actions":{"Actions":[{"__type":"adjustvar","variable":"_disabled","operator":"set","value":{"type":"boolean","value":true}},{"__type":"exe_actiongroup","id":"_player._setstates","scoperef":{"type":"string","value":"_this"},"params":null}]}},{"__type":"actiongroup","id":"ActGrpSetDownState","actions":{"Actions":[{"__type":"adjustvar","variable":"_down","operator":"set","value":{"type":"boolean","value":true}},{"__type":"exe_actiongroup","id":"_player._setstates","scoperef":{"type":"string","value":"_this"},"params":null}]}},{"__type":"actiongroup","id":"ActGrpClearStateVars","actions":{"Actions":[{"__type":"adjustvar","variable":"_hover","operator":"set","value":{"type":"boolean","value":false}},{"__type":"adjustvar","variable":"_down","operator":"set","value":{"type":"boolean","value":false}},{"__type":"adjustvar","variable":"_visited","operator":"set","value":{"type":"boolean","value":false}},{"__type":"adjustvar","variable":"_disabled","operator":"set","value":{"type":"boolean","value":false}},{"__type":"adjustvar","variable":"_savevisited","operator":"set","value":{"type":"boolean","value":false}}]}}],"events":[{"__type":"onrelease","actions":{"Actions":[{"__type":"exe_actiongroup","id":"ActGrpSetVisitedState","scoperef":{"type":"string","value":"_this"},"params":null},{"__type":"adjustvar","variable":"_down","operator":"set","value":{"type":"boolean","value":false}},{"__type":"exe_actiongroup","id":"_player._setstates","scoperef":{"type":"string","value":"_this"},"params":null},{"__type":"show_slidelayer","hideothers":"oncomplete","transition":"appear","duration":0,"direction":1,"animationid":null,"reverse":false,"objref":{"type":"string","value":"_parent._parent.5jE35qsKXif"}}]}},{"__type":"ontransitionin","actions":{"Actions":[{"__type":"exe_actiongroup","id":"_player._setstates","scoperef":{"type":"string","value":"_this"},"params":null}]}},{"__type":"onrollover","actions":{"Actions":[{"__type":"exe_actiongroup","id":"ActGrpSetHoverState","scoperef":{"type":"string","value":"_this"},"params":null}]}},{"__type":"onrollout","actions":{"Actions":[{"__type":"exe_actiongroup","id":"ActGrpClearHoverState","scoperef":{"type":"string","value":"_this"},"params":null}]}},{"__type":"onpress","actions":{"Actions":[{"__type":"exe_actiongroup","id":"ActGrpSetDownState","scoperef":{"type":"string","value":"_this"},"params":null}]}},{"__type":"onreleaseoutside","actions":{"Actions":[{"__type":"adjustvar","variable":"_down","operator":"set","value":{"type":"boolean","value":false}},{"__type":"exe_actiongroup","id":"_player._setstates","scoperef":{"type":"string","value":"_this"},"params":null}]}}]}]},"starttime":-1,"elapsedtimemode":"normal","width":720,"height":540,"resume":true,"usehandcursor":false,"background":null,"id":"67w0T79iCZz"}],"showanimationid":"","enableseek":true,"enablereplay":true,"lmsid":"Slide7","timeline":{"duration":188995,"events":[{"__type":"event","time":0,"actions":{"Actions":[{"__type":"show","transition":"appear","duration":0,"direction":0,"animationid":"","reverse":false,"objref":{"type":"string","value":"6eJCiIXFkdo"}}]}}]},"objects":{"Objects":[{"__type":"vectorshape","rotation":0,"acctype":"text","defaultaction":"","textlib":[{"__type":"textdata","uniqueId":"6eJCiIXFkdo_-305012878","id":"01","linkid":"txt__default_6eJCiIXFkdo","type":"vectortext","alttext":null,"lmstext":null,"xpos":0,"ypos":0,"width":0,"height":0,"shadowindex":-1,"vartext":null,"vectortext":{"left":0,"top":0,"right":190,"bottom":27,"alttext":null,"lmstext":null,"pngfb":false,"pr":{"l":"Lib","i":45},"text":null}}],"shapemaskid":"","xpos":72,"ypos":46,"tabindex":7,"tabenabled":true,"xoffset":0,"yoffset":0,"rotatexpos":100,"rotateypos":16,"xscale":100,"yscale":100,"alpha":100,"depth":1,"scrolling":true,"shufflelock":false,"dragdrop":null,"dragpath":null,"dragrotation":null,"data":{"hotlinkid":"","accstate":0,"textdata":null,"imagedata":null,"swfdata":null,"videodata":null,"audiodata":null,"emfdata":null,"rectdata":null,"vectordata":{"left":0,"top":0,"right":200,"bottom":32,"alttext":"6. A Little Bit Softer Now","lmstext":null,"pngfb":false,"pr":{"l":"Lib","i":44},"text":null},"html5data":{"url":null,"xpos":-1,"ypos":-1,"width":201,"height":33,"strokewidth":0,"mask":null}},"mask":null,"markerType":null,"width":200,"height":32,"resume":false,"usehandcursor":true,"background":null,"id":"6eJCiIXFkdo"}]},"starttime":-1,"elapsedtimemode":"normal","width":720,"height":540,"resume":false,"usehandcursor":false,"background":{"type":"fill","fill":{"type":"linear","rotation":90,"colors":[{"__type":"color","rgb":"0x000000","alpha":100,"stop":0}]},"imagedata":null,"emfdata":null,"vectordata":null},"id":"60v2edlHkFF","events":[{"__type":"onslidestart","actions":{"Actions":[{"__type":"show_slidelayer","hideothers":"oncomplete","transition":"appear","duration":0,"direction":1,"animationid":null,"reverse":false,"objref":{"type":"string","value":"5jE35qsKXif"}}]}},{"__type":"onbeforeslidein","actions":{"Actions":[{"__type":"if_action","condition":{"Statement":{"__type":"compare","operator":"eq","valuea":"WindowId","typea":"property","valueb":"_frame","typeb":"string"}},"then_actions":{"Actions":[{"__type":"set_frame_layout","name":"npnxnsnfns00000000001"}]},"else_actions":{"Actions":[{"__type":"set_window_control_layout","name":"npnxnsnfns00000000001"}]}}]}},{"__type":"ontransitionin","actions":{"Actions":[{"__type":"adjustvar","variable":"_player.LastSlideViewed_6HUzA3p9Uhm","operator":"set","value":{"type":"string","value":"_player."}},{"__type":"adjustvar","variable":"_player.LastSlideViewed_6HUzA3p9Uhm","operator":"add","value":{"type":"property","value":"AbsoluteId"}}]}}]}
